cmem_plugin_validation/__init__.py
cmem_plugin_validation/validate_entities/__init__.py
cmem_plugin_validation/validate_entities/icon.svg
cmem_plugin_validation/validate_entities/state.py
cmem_plugin_validation/validate_entities/task.py
cmem_plugin_validation/validate_graph/__init__.py
cmem_plugin_validation/validate_graph/icon.svg
cmem_plugin_validation/validate_graph/state.py
cmem_plugin_validation/validate_graph/task.py
cmem_plugin_validation-1.2.0.dist-info/METADATA
cmem_plugin_validation-1.2.0.dist-info/WHEEL
cmem_plugin_validation-1.2.0.dist-info/licenses/LICENSE
cmem_plugin_validation-1.2.0.dist-info/RECORD
